asgard/__init__.py
asgard/core/__init__.py
asgard/core/body.py
asgard/core/frame.py
asgard/core/logger.py
asgard/core/math.cpython-311-x86_64-linux-gnu.so
asgard/core/math.pyi
asgard/core/model.py
asgard/core/orbit.py
asgard/core/platform.py
asgard/core/pointing.py
asgard/core/product.py
asgard/core/propagation.py
asgard/core/schema.py
asgard/core/target.py
asgard/core/time.py
asgard/core/timestamp.py
asgard/core/toolbox.py
asgard/core/transform.py
asgard/models/__init__.py
asgard/models/attitude.py
asgard/models/body.py
asgard/models/crosstrack.py
asgard/models/dem.py
asgard/models/linedetector.py
asgard/models/orbit.py
asgard/models/platform.py
asgard/models/propagation.py
asgard/models/range.py
asgard/models/sar.py
asgard/models/scanningdetector.py
asgard/models/thermoelastic.py
asgard/models/time.py
asgard/sensors/__init__.py
asgard/sensors/synthetic.py
asgard/sensors/sentinel1/__init__.py
asgard/sensors/sentinel1/csar.py
asgard/sensors/sentinel1/l0.py
asgard/sensors/sentinel2/__init__.py
asgard/sensors/sentinel2/msi.py
asgard/sensors/sentinel2/s2_band.py
asgard/sensors/sentinel2/s2_constants.py
asgard/sensors/sentinel2/s2_detector.py
asgard/sensors/sentinel2/s2_sensor.py
asgard/sensors/sentinel3/__init__.py
asgard/sensors/sentinel3/l0.py
asgard/sensors/sentinel3/mwr.py
asgard/sensors/sentinel3/olci.py
asgard/sensors/sentinel3/slstr.py
asgard/sensors/sentinel3/sral.py
asgard/wrappers/__init__.py
asgard/wrappers/orekit/__init__.py
asgard/wrappers/orekit/jcc_util.py
asgard/wrappers/orekit/utils.py
asgard_eopf-1.3.7.dist-info/METADATA
asgard_eopf-1.3.7.dist-info/WHEEL
asgard_eopf-1.3.7.dist-info/top_level.txt
asgard_eopf-1.3.7.dist-info/RECORD
asgard_eopf-1.3.7.dist-info/licenses/LICENSE
