Metadata-Version: 2.4
Name: asgard_eopf
Version: 1.3.7
Summary: A Sensor Geometry Application Re-usable by-Design
Author-email: CS Group <cs.eopf-geolib@cs-soprasteria.com>
Project-URL: Homepage, https://gitlab.eopf.copernicus.eu/geolib/asgard
Project-URL: Documentation, https://geolib.pages.eopf.copernicus.eu/asgard/
Project-URL: Repository, https://gitlab.eopf.copernicus.eu/geolib/asgard.git
Project-URL: Issues, https://gitlab.eopf.copernicus.eu/geolib/asgard/-/issues
Project-URL: Changelog, https://gitlab.eopf.copernicus.eu/geolib/asgard/-/blob/main/CHANGELOG.md
Keywords: asgard,rugged,orekit,hipparchus,eopf
Classifier: Development Status :: 5 - Production/Stable
Classifier: Programming Language :: Python
Classifier: Programming Language :: Python :: 3
Classifier: Programming Language :: Python :: 3.11
Classifier: Programming Language :: Python :: 3.12
Classifier: Programming Language :: Python :: 3.13
Classifier: Programming Language :: Python :: 3.14
Classifier: Programming Language :: Python :: 3 :: Only
Classifier: Programming Language :: Python :: Implementation :: CPython
Classifier: Operating System :: POSIX
Classifier: Operating System :: Unix
Requires-Python: >=3.8
License-File: LICENSE
Requires-Dist: orekit-jcc<13.3,>=13.2
Requires-Dist: pyrugged<1.2,>=1.1.6
Requires-Dist: forbiddenfruit>=0.1.4
Requires-Dist: scikit-learn>=1.3.0
Requires-Dist: s3fs==2024.5.0
Requires-Dist: numcodecs==0.15.1
Requires-Dist: zarr==2.18.4
Requires-Dist: numpy>=2.1.0
Requires-Dist: xarray==2025.9.0
Requires-Dist: jsonschema==4.23.0
Dynamic: license-file
